rainer/__init__.py
rainer/analyse.py
rainer/io.py
rainer/plot.py
rainer/rainer_classes.py
rainer-0.0.6.dist-info/LICENSE
rainer-0.0.6.dist-info/METADATA
rainer-0.0.6.dist-info/WHEEL
rainer-0.0.6.dist-info/top_level.txt
rainer-0.0.6.dist-info/RECORD
