Metadata-Version: 2.1
Name: rainer
Version: 0.0.6
Summary: Wacky tool for fMRI analysis
Author: Hendrik Mattern
Maintainer: Hendrik Mattern
License: MIT License
Project-URL: Repository, https://github.com/hendrikmattern/RAINER.git
Classifier: Programming Language :: Python
Requires-Python: >=3.8
License-File: LICENSE
